concertina/__init__.py
concertina/templatetags/__init__.py
concertina/templatetags/concertina_pagination.py
django_concertina-1.0.1.dist-info/DESCRIPTION.rst
django_concertina-1.0.1.dist-info/METADATA
django_concertina-1.0.1.dist-info/metadata.json
django_concertina-1.0.1.dist-info/RECORD
django_concertina-1.0.1.dist-info/top_level.txt
django_concertina-1.0.1.dist-info/WHEEL
