Metadata-Version: 2.0
Name: django-concertina
Version: 1.0.1
Summary: Django template tag to provide concertina pagination.
Home-page: https://github.com/norm/django-concertina
Author: Mark Norman Francis
Author-email: norm@201created.com
License: MIT
Platform: UNKNOWN
Classifier: Intended Audience :: Developers
Classifier: Framework :: Django
Classifier: License :: OSI Approved :: MIT License
Classifier: Programming Language :: Python :: 2
Classifier: Programming Language :: Python :: 3
Requires-Dist: Django (>=1.6.0)
